seg1d/__init__.py
seg1d/_about.py
seg1d/_version.py
seg1d/algorithm.py
seg1d/optimized_funcs.py
seg1d/segment.py
seg1d/examples/__init__.py
seg1d/examples/ex_ecg.py
seg1d/examples/ex_gauss.py
seg1d/examples/ex_multi_signal.py
seg1d/examples/ex_segment_class.py
seg1d/examples/ex_segmenter_features.py
seg1d/examples/ex_segmenter_sine.py
seg1d/examples/ex_simple.py
seg1d/examples/ex_sine.py
seg1d/examples/ex_sine_noise.py
seg1d/examples/ex_sine_noise_few.py
seg1d/examples/ex_sine_scale.py
seg1d/examples/noise.py
seg1d/examples/test.py
seg1d/examples/data/r.npy
seg1d/examples/data/t.npy
seg1d/examples/data/w.npy
seg1d-0.1.0.dist-info/LICENSE.txt
seg1d-0.1.0.dist-info/METADATA
seg1d-0.1.0.dist-info/WHEEL
seg1d-0.1.0.dist-info/top_level.txt
seg1d-0.1.0.dist-info/RECORD
