Metadata-Version: 2.1
Name: seg1d
Version: 0.1.0
Summary: Automated one-dimensional subsequence segmentation
Home-page: https://github.com/cadop/seg1d
Author: Mathew Schwartz
Author-email: umcadop@gmail.com
License: UNKNOWN
Platform: UNKNOWN
Classifier: Programming Language :: Python :: 3
Classifier: License :: OSI Approved :: GNU General Public License v3 (GPLv3)
Classifier: Operating System :: OS Independent
Requires-Python: >=3.6
Requires-Dist: numpy (>=1.15)
Requires-Dist: scipy (>=1.0.0)
Requires-Dist: scikit-learn (>=0.2)
Requires-Dist: numba (>=0.40.0)
